ldc_vortex_datalayer-0.0.3.dist-info/licenses/LICENSE
vortex_datalayer/__init__.py
vortex_datalayer/base_layer.py
vortex_datalayer/cache_manager.py
vortex_datalayer/constants.py
vortex_datalayer/redis_utils.py
vortex_datalayer/ddl/repayment_system_schema.sql
vortex_datalayer/entity/__init__.py
vortex_datalayer/entity/account.py
vortex_datalayer/entity/borrower.py
vortex_datalayer/entity/calculation.py
vortex_datalayer/entity/channel_partner_mapping.py
vortex_datalayer/entity/common_repayment_transfer.py
vortex_datalayer/entity/common_table_repayment_migration_logs.py
vortex_datalayer/entity/entity.py
vortex_datalayer/entity/investment_loan_detail.py
vortex_datalayer/entity/investment_loan_redemption_summary.py
vortex_datalayer/entity/investment_loan_repayment_summary.py
vortex_datalayer/entity/investment_product_config.py
vortex_datalayer/entity/job_log.py
vortex_datalayer/entity/job_master.py
vortex_datalayer/entity/ledger.py
vortex_datalayer/entity/lendenapp_transaction_file_logs.py
vortex_datalayer/entity/lender.py
vortex_datalayer/entity/lender_investment.py
vortex_datalayer/entity/lender_investment_order.py
vortex_datalayer/entity/lender_redemption.py
vortex_datalayer/entity/lender_wallet_tracker.py
vortex_datalayer/entity/loan.py
vortex_datalayer/entity/loan_analytics.py
vortex_datalayer/entity/loan_event_queue.py
vortex_datalayer/entity/loan_fees_config.py
vortex_datalayer/entity/loan_portfolio_details_temp.py
vortex_datalayer/entity/loan_product_config.py
vortex_datalayer/entity/loan_repayment_summary.py
vortex_datalayer/entity/master_account.py
vortex_datalayer/entity/mst_parameter.py
vortex_datalayer/entity/otl_product_config.py
vortex_datalayer/entity/preference.py
vortex_datalayer/entity/redemption_detail.py
vortex_datalayer/entity/redemption_summary.py
vortex_datalayer/entity/repayment_batch_summary.py
vortex_datalayer/entity/retail_portfolio_calculation_queue.py
vortex_datalayer/entity/retail_portfolio_summary.py
vortex_datalayer/entity/scheme_loan_mapping.py
vortex_datalayer/entity/transaction_id.py
ldc_vortex_datalayer-0.0.3.dist-info/METADATA
ldc_vortex_datalayer-0.0.3.dist-info/WHEEL
ldc_vortex_datalayer-0.0.3.dist-info/top_level.txt
ldc_vortex_datalayer-0.0.3.dist-info/RECORD
