Metadata-Version: 2.4
Name: LDC_Vortex-Datalayer
Version: 0.0.3
Summary: A comprehensive data access layer for Vortex apps
Author: Sonu Sharma
Author-email: sonu.sharma@lendenclub.com
Maintainer: Sonu Sharma
Maintainer-email: sonu.sharma@lendenclub.com
Classifier: Intended Audience :: Developers
Classifier: Programming Language :: Python :: 3
Classifier: Topic :: Utilities
Requires-Python: >=3.10.0
License-File: LICENSE
Requires-Dist: Django>=5.2.0
Requires-Dist: psycopg[binary,pool]>=3.2.9
Requires-Dist: redis>=5.0.3
Requires-Dist: pytz>=2024.1
Dynamic: author
Dynamic: author-email
Dynamic: classifier
Dynamic: description
Dynamic: description-content-type
Dynamic: license-file
Dynamic: maintainer
Dynamic: maintainer-email
Dynamic: requires-dist
Dynamic: requires-python
Dynamic: summary
